{
  "accentColor": "{{appsmith.theme.colors.primaryColor}}",
  "animateLoading": true,
  "autoFocus": false,
  "borderRadius": "{{appsmith.theme.borderRadius.appBorderRadius}}",
  "bottomRow": 14,
  "boxShadow": "none",
  "defaultText": "",
  "dynamicBindingPathList": [
    {
      "key": "accentColor"
    },
    {
      "key": "borderRadius"
    }
  ],
  "dynamicHeight": "FIXED",
  "dynamicTriggerPathList": [],
  "iconAlign": "left",
  "inputType": "TEXT",
  "isDisabled": false,
  "isLoading": false,
  "isRequired": false,
  "isVisible": true,
  "key": "tze0umlijr",
  "label": "Số Lượng Thực Xuất",
  "labelAlignment": "left",
  "labelPosition": "Top",
  "labelStyle": "",
  "labelTextSize": "0.875rem",
  "labelWidth": 5,
  "leftColumn": 0,
  "maxDynamicHeight": 9000,
  "minDynamicHeight": 4,
  "minWidth": 450,
  "mobileBottomRow": 41,
  "mobileLeftColumn": 0,
  "mobileRightColumn": 20,
  "mobileTopRow": 34,
  "needsErrorInfo": false,
  "originalBottomRow": 26,
  "originalTopRow": 19,
  "parentColumnSpace": 17.237060546875,
  "parentId": "8vmw52irpm",
  "parentRowSpace": 10,
  "renderMode": "CANVAS",
  "resetOnSubmit": true,
  "responsiveBehavior": "fill",
  "rightColumn": 37,
  "showStepArrows": false,
  "topRow": 7,
  "type": "INPUT_WIDGET_V2",
  "version": 2,
  "widgetId": "51je4coyfv",
  "widgetName": "inp_sl_khac"
}